<?xml version="1.0" encoding="UTF-8"?>
<rules minver="1.1.6">
    <rule name="postMessageSupport" value="true">
        <group type="or">
            <group type="and">
                <eq field="BrowserName">MSIE</eq>
                <gte field="BrowserVersion">8</gte>
            </group>
            <group type="and">
                <eq field="BrowserName">Edge</eq>
                <gte field="BrowserEngine">Edge</gte>
            </group>
            <group type="and">
                <eq field="BrowserName">Firefox</eq>
                <gte field="BrowserVersion">3</gte>
            </group>
            <group type="and">
                <eq field="BrowserName">Chrome</eq>
                <gte field="BrowserVersion">4</gte>
            </group>
            <group type="and">
                <eq field="BrowserBase">Chromium</eq>
                <gte field="BrowserBaseVersion">4</gte>
            </group>
            <group type="and">
                <eq field="BrowserName">ChromeMobile</eq>
                <gte field="BrowserVersion">33</gte>
            </group>
            <group type="and">
                <eq field="BrowserBase">Safari</eq>
                <gte field="BrowserBaseVersion">4</gte>
            </group>
            <group type="and">
                <eq field="BrowserName">Opera</eq>
                <gte field="BrowserVersion">9.5</gte>
            </group>
            <group type="and">
                <eq field="BrowserName">MobileSafari</eq>
                <gte field="BrowserVersion">3.2</gte>
            </group>
            <group type="and">
                <eq field="BrowserName">AndroidBrowser</eq>
                <gte field="BrowserVersion">4</gte>
            </group>
            <group type="and">
                <eq field="BrowserName">BlackBerry</eq>
                <gte field="BrowserVersion">7</gte>
            </group>
            <group type="and">
                <eq field="BrowserName">OperaMobile</eq>
                <gte field="BrowserVersion">10</gte>
            </group>
            <group type="and">
                <eq field="BrowserName">IEMobile</eq>
                <gte field="BrowserVersion">10</gte>
            </group>
            <group type="and">
                <eq field="BrowserName">MobileFirefox</eq>
                <gte field="BrowserVersion">31</gte>
            </group>
            <group type="and">
                <eq field="BrowserBase">YandexBrowser</eq>
            </group>
        </group>
    </rule>
    <rule name="historySupport" value="true">
        <group type="or">
            <group type="and">
                <eq field="BrowserName">MSIE</eq>
                <gte field="BrowserVersion">10</gte>
            </group>
            <group type="and">
                <eq field="BrowserName">Edge</eq>
                <gte field="BrowserEngine">Edge</gte>
            </group>
            <group type="and">
                <eq field="BrowserName">Firefox</eq>
                <gte field="BrowserVersion">4</gte>
            </group>
            <group type="and">
                <eq field="BrowserName">Chrome</eq>
                <gte field="BrowserVersion">5</gte>
            </group>
            <group type="and">
                <eq field="BrowserBase">Chromium</eq>
                <gte field="BrowserBaseVersion">5</gte>
            </group>
            <group type="and">
                <eq field="BrowserName">ChromeMobile</eq>
                <gte field="BrowserVersion">33</gte>
            </group>
            <group type="and">
                <eq field="BrowserBase">Safari</eq>
                <gte field="BrowserBaseVersion">5.1</gte>
            </group>
            <group type="and">
                <eq field="BrowserName">Opera</eq>
                <gte field="BrowserVersion">11.5</gte>
            </group>
            <group type="and">
                <eq field="BrowserName">MobileSafari</eq>
                <gte field="BrowserVersion">5.0</gte>
            </group>
            <group type="and">
                <eq field="BrowserName">AndroidBrowser</eq>
                <gte field="BrowserVersion">4.2</gte>
            </group>
            <group type="and">
                <eq field="BrowserName">BlackBerry</eq>
                <gte field="BrowserVersion">7</gte>
            </group>
            <group type="and">
                <eq field="BrowserName">IEMobile</eq>
                <gte field="BrowserVersion">10</gte>
            </group>
            <group type="and">
                <eq field="BrowserName">MobileFirefox</eq>
                <gte field="BrowserVersion">31</gte>
            </group>
            <group type="and">
                <eq field="BrowserName">OperaMobile</eq>
                <gte field="BrowserVersion">11.5</gte>
            </group>
            <group type="and">
                <eq field="BrowserBase">YandexBrowser</eq>
            </group>
        </group>
    </rule>
    <rule name="localStorageSupport" value="true">
        <group type="or">
            <group type="and">
                <eq field="BrowserName">MSIE</eq>
                <gte field="BrowserVersion">8</gte>
            </group>
            <group type="and">
                <eq field="BrowserName">Edge</eq>
                <gte field="BrowserEngine">Edge</gte>
            </group>
            <group type="and">
                <eq field="BrowserName">Firefox</eq>
                <gte field="BrowserVersion">3.5</gte>
            </group>
            <group type="and">
                <eq field="BrowserName">Chrome</eq>
                <gte field="BrowserVersion">4</gte>
            </group>
            <group type="and">
                <eq field="BrowserName">ChromeMobile</eq>
                <gte field="BrowserVersion">33</gte>
            </group>
            <group type="and">
                <eq field="BrowserBase">Chromium</eq>
                <gte field="BrowserBaseVersion">4</gte>
            </group>
            <group type="and">
                <eq field="BrowserBase">Safari</eq>
                <gte field="BrowserBaseVersion">4</gte>
            </group>
            <group type="and">
                <eq field="BrowserName">Opera</eq>
                <gte field="BrowserVersion">10.5</gte>
            </group>
            <group type="and">
                <eq field="BrowserName">MobileSafari</eq>
                <gte field="BrowserVersion">3.2</gte>
            </group>
            <group type="and">
                <eq field="BrowserName">AndroidBrowser</eq>
                <gte field="BrowserVersion">2.1</gte>
            </group>
            <group type="and">
                <eq field="BrowserName">BlackBerry</eq>
                <gte field="BrowserVersion">7</gte>
            </group>
            <group type="and">
                <eq field="BrowserName">IEMobile</eq>
                <gte field="BrowserVersion">10</gte>
            </group>
            <group type="and">
                <eq field="BrowserName">MobileFirefox</eq>
                <gte field="BrowserVersion">31</gte>
            </group>
            <group type="and">
                <eq field="BrowserName">OperaMobile</eq>
                <gte field="BrowserVersion">11.5</gte>
            </group>
            <group type="and">
                <eq field="BrowserBase">YandexBrowser</eq>
            </group>
        </group>
    </rule>
    <rule name="SVGSupport" value="true">
        <group type="or">
            <group type="and">
                <eq field="BrowserName">MSIE</eq>
                <gte field="BrowserVersion">9</gte>
            </group>
            <group type="and">
                <eq field="BrowserName">Edge</eq>
                <gte field="BrowserEngine">Edge</gte>
            </group>
            <group type="and">
                <eq field="BrowserName">Firefox</eq>
                <gte field="BrowserVersion">3</gte>
            </group>
            <group type="and">
                <eq field="BrowserName">Chrome</eq>
                <gte field="BrowserVersion">4</gte>
            </group>
            <group type="and">
                <eq field="BrowserBase">Chromium</eq>
                <gte field="BrowserBaseVersion">4</gte>
            </group>
            <group type="and">
                <eq field="BrowserName">ChromeMobile</eq>
                <gte field="BrowserVersion">37</gte>
            </group>
            <group type="and">
                <eq field="BrowserBase">Safari</eq>
                <gte field="BrowserBaseVersion">3.2</gte>
            </group>
            <group type="and">
                <eq field="BrowserName">Opera</eq>
                <gte field="BrowserVersion">9.6</gte>
            </group>
            <group type="and">
                <eq field="BrowserName">MobileSafari</eq>
                <gte field="BrowserVersion">3.2</gte>
            </group>
            <group type="and">
                <eq field="BrowserName">AndroidBrowser</eq>
                <gte field="BrowserVersion">4</gte>
            </group>
            <group type="and">
                <eq field="BrowserName">BlackBerry</eq>
                <gte field="BrowserVersion">7</gte>
            </group>
            <group type="and">
                <eq field="BrowserName">OperaMobile</eq>
                <gte field="BrowserVersion">10</gte>
            </group>
            <group type="and">
                <eq field="BrowserName">IEMobile</eq>
                <gte field="BrowserVersion">10</gte>
            </group>
            <group type="and">
                <eq field="BrowserName">MobileFirefox</eq>
                <gte field="BrowserVersion">32</gte>
            </group>
            <group type="and">
                <eq field="BrowserName">YandexSearch</eq>
                <gte field="BrowserVersion">1</gte>
            </group>
        </group>
    </rule>
    <rule name="WebPSupport" value="true">
        <group type="or">
            <group type="and">
                <eq field="BrowserName">Chrome</eq>
                <gte field="BrowserVersion">23</gte>
            </group>
            <group type="and">
                <eq field="BrowserBase">Chromium</eq>
                <gte field="BrowserBaseVersion">23</gte>
            </group>
            <group type="and">
                <eq field="BrowserName">ChromeMobile</eq>
                <eq field="OSFamily">Android</eq>
                <gte field="BrowserVersion">38</gte>
            </group>
            <group type="and">
                <eq field="BrowserName">Opera</eq>
                <gte field="BrowserVersion">12</gte>
            </group>
            <group type="and">
                <eq field="BrowserName">OperaMini</eq>
                <gte field="BrowserVersion">8</gte>
            </group>
            <group type="and">
                <eq field="BrowserName">AndroidBrowser</eq>
                <gte field="BrowserVersion">4.3</gte>
            </group>
            <group type="and">
                <eq field="BrowserName">OperaMobile</eq>
                <gte field="BrowserVersion">11.5</gte>
            </group>
            <group type="and">
                <eq field="BrowserName">Edge</eq>
                <gte field="BrowserVersion">18</gte>
            </group>
            <group type="and">
                <eq field="BrowserName">Firefox</eq>
                <gte field="BrowserVersion">65</gte>
            </group>
            <group type="and">
                <eq field="BrowserName">MobileFirefox</eq>
                <eq field="OSFamily">Android</eq>
                <gte field="BrowserVersion">65</gte>
            </group>
            <group type="and">
                <eq field="BrowserBase">YandexBrowser</eq>
            </group>
        </group>
    </rule>
    <rule name="CSP2Support" value="true">
        <group type="or">
            <group type="and">
                <eq field="BrowserName">Edge</eq>
                <gte field="BrowserVersion">19</gte>
            </group>
            <group type="and">
                <eq field="BrowserName">Chrome</eq>
                <gte field="BrowserVersion">40</gte>
            </group>
            <!--<group type="and">-->
                <!--<eq field="BrowserName">Firefox</eq>-->
                <!--<gte field="BrowserVersion">31</gte>-->
            <!--</group>-->
            <group type="and">
                <eq field="BrowserName">Safari</eq>
                <gte field="BrowserVersion">10</gte>
            </group>
            <group type="and">
                <eq field="BrowserName">Opera</eq>
                <gte field="BrowserVersion">27</gte>
            </group>
            <group type="and">
                <eq field="BrowserName">MobileSafari</eq>
                <gte field="BrowserVersion">10</gte>
            </group>
            <group type="and">
                <eq field="BrowserBase">Chromium</eq>
                <gte field="BrowserBaseVersion">40</gte>
            </group>
            <group type="and">
                <eq field="BrowserName">OperaMobile</eq>
                <eq field="OSFamily">Android</eq>
                <gte field="BrowserVersion">37</gte>
            </group>
            <group type="and">
                <eq field="BrowserName">ChromeMobile</eq>
                <eq field="OSFamily">Android</eq>
                <gte field="BrowserVersion">51</gte>
            </group>
            <!--<group type="and">-->
                <!--<eq field="BrowserName">MobileFirefox</eq>-->
                <!--<eq field="OSFamily">Android</eq>-->
                <!--<gte field="BrowserVersion">23</gte>-->
            <!--</group>-->
            <group type="and">
                <eq field="BrowserName">Samsung Internet</eq>
                <gte field="BrowserVersion">4</gte>
            </group>
            <group type="and">
                <eq field="BrowserName">MQQBrowser</eq>
                <gte field="BrowserVersion">1.2</gte>
            </group>
            <group type="and">
                <eq field="BrowserName">Baidu</eq>
                <gte field="BrowserVersion">7.12</gte>
            </group>
            <group type="and">
                <eq field="BrowserBase">YandexBrowser</eq>
            </group>
        </group>
    </rule>
    <rule name="CSP1Support" value="true">
        <group type="or">
            <group type="and">
                <eq field="BrowserName">Edge</eq>
                <gte field="BrowserVersion">14</gte>
            </group>
            <group type="and">
                <eq field="BrowserName">MSIE</eq>
                <gte field="BrowserVersion">12</gte>
            </group>
            <group type="and">
                <eq field="BrowserName">Chrome</eq>
                <gte field="BrowserVersion">14</gte>
            </group>
            <group type="and">
                <eq field="BrowserName">Firefox</eq>
                <gte field="BrowserVersion">4</gte>
            </group>
            <group type="and">
                <eq field="BrowserName">Safari</eq>
                <gte field="BrowserVersion">6</gte>
            </group>
            <group type="and">
                <eq field="BrowserName">Opera</eq>
                <gte field="BrowserVersion">15</gte>
            </group>
            <group type="and">
                <eq field="BrowserName">MobileSafari</eq>
                <gte field="BrowserVersion">6.1</gte>
            </group>
            <group type="and">
                <eq field="BrowserBase">Chromium</eq>
                <gte field="BrowserBaseVersion">14</gte>
            </group>
            <group type="and">
                <eq field="BrowserName">AndroidBrowser</eq>
                <gte field="BrowserVersion">4.4</gte>
            </group>
            <group type="and">
                <eq field="BrowserName">OperaMobile</eq>
                <eq field="OSFamily">Android</eq>
                <gte field="BrowserVersion">37</gte>
            </group>
            <group type="and">
                <eq field="BrowserName">ChromeMobile</eq>
                <eq field="OSFamily">Android</eq>
                <gte field="BrowserVersion">51</gte>
            </group>
            <group type="and">
                <eq field="BrowserName">MobileFirefox</eq>
                <eq field="OSFamily">Android</eq>
                <gte field="BrowserVersion">23</gte>
            </group>
            <group type="and">
                <eq field="BrowserName">Samsung Internet</eq>
                <gte field="BrowserVersion">4</gte>
            </group>
            <group type="and">
                <eq field="BrowserName">BlackBerry</eq>
                <gte field="BrowserVersion">10</gte>
            </group>
            <group type="and">
                <eq field="BrowserName">IEMobile</eq>
                <gte field="BrowserVersion">10</gte>
            </group>
            <group type="and">
                <eq field="BrowserName">MQQBrowser</eq>
                <gte field="BrowserVersion">1.2</gte>
            </group>
            <group type="and">
                <eq field="BrowserName">Baidu</eq>
                <gte field="BrowserVersion">7.12</gte>
            </group>
            <group type="and">
                <eq field="BrowserBase">YandexBrowser</eq>
            </group>
        </group>
    </rule>
    <rule name="ITPFakeCookie" value="true">
        <group type="or">
            <group type="and">
                <eq field="OSFamily">iOS</eq>
                <eq field="BrowserName">MobileSafari</eq>
                <gte field="OSVersion">11</gte>
                <lt field="OSVersion">12.2</lt>
            </group>
            <group type="and">
                <eq field="OSFamily">MacOS</eq>
                <eq field="BrowserName">Safari</eq>
                <gte field="OSVersion">10.13</gte>
            </group>
        </group>
    </rule>
    <rule name="ITP" value="true">
        <group type="or">
            <group type="or">
                <group type="and">
                    <eq field="OSFamily">iOS</eq>
                    <eq field="BrowserName">MobileSafari</eq>
                    <gte field="OSVersion">11</gte>
                </group>
                <group type="and">
                    <eq field="OSFamily">MacOS</eq>
                    <eq field="BrowserName">Safari</eq>
                    <gte field="OSVersion">10.13</gte>
                </group>
            </group>
            <group type="or">
                <group type="and">
                    <eq field="BrowserName">Firefox</eq>
                    <gte field="BrowserVersion">69</gte>
                </group>
                <group type="and">
                    <eq field="BrowserName">MobileFirefox</eq>
                    <gte field="BrowserVersion">69</gte>
                </group>
                <group type="and">
                    <eq field="BrowserName">MobileFirefox</eq>
                    <eq field="OSFamily">iOS</eq>
                    <gte field="BrowserVersion">19</gte>
                </group>
                <group type="and">
                    <eq field="BrowserName">Edge</eq>
                    <gte field="BrowserVersion">80</gte>
                </group>
            </group>
            <group type="and">
                <eq field="BrowserName">YandexBrowser</eq>
                <gte field="YaITPExpVersion">50</gte>
                <lte field="YaITPExpVersion">99</lte>
            </group>
            <group type="and">
                    <eq field="OSFamily">iOS</eq>
                    <gte field="OSVersion">14</gte>
            </group>
        </group>
    </rule>
    <rule name="ITPMaybe" value="true">
        <group type="or">
            <group type="and">
                <eq field="BrowserName">Firefox</eq>
                <gte field="BrowserVersion">67</gte>
                <lt field="BrowserVersion">69</lt>
            </group>
            <group type="and">
                <eq field="BrowserName">MobileFirefox</eq>
                <gte field="BrowserVersion">67</gte>
                <lt field="BrowserVersion">69</lt>
            </group>
            <group type="and">
                <eq field="BrowserName">Edge</eq>
                <gte field="BrowserVersion">78</gte>
                <lt field="BrowserVersion">80</lt>
            </group>
        </group>
    </rule>
    <rule name="AntiITP" value="true">
        <group type="or">
            <eq field="BrowserName">Safari</eq>
            <eq field="BrowserName">MobileSafari</eq>
            <eq field="BrowserName">Firefox</eq>
            <eq field="BrowserName">MobileFirefox</eq>
            <eq field="BrowserName">Edge</eq>
            <group type="and">
                <eq field="OSFamily">iOS</eq>
                <gte field="OSVersion">14</gte>
            </group>
        </group>
    </rule>
    <rule name="SameSiteSupport" value="true">
        <group type="or">
            <group type="and">
                <eq field="BrowserName">Chrome</eq>
                <gte field="BrowserVersion">76</gte>
            </group>
            <group type="and">
                <eq field="BrowserName">ChromeMobile</eq>
                <eq field="OSFamily">iOS</eq>
                <gte field="OSVersion">13</gte>
                <gte field="BrowserVersion">76</gte>
            </group>
            <group type="and">
                <eq field="BrowserName">ChromeMobile</eq>
                <eq field="OSFamily">Android</eq>
                <gte field="BrowserVersion">76</gte>
            </group>
            <group type="and">
                <eq field="BrowserName">Opera</eq>
                <gte field="BrowserVersion">63</gte>
            </group>
            <group type="and">
                <neq field="BrowserName">Chrome</neq>
                <neq field="BrowserName">ChromeMobile</neq>
                <neq field="BrowserName">YandexBrowser</neq>
                <neq field="BrowserName">Opera</neq>
                <eq field="BrowserBase">Chromium</eq>
                <gte field="BrowserBaseVersion">76</gte>
            </group>
        </group>
    </rule>
</rules>
